DirectPy.py
README.md
setup.cfg
setup.py
directpy.egg-info/PKG-INFO
directpy.egg-info/SOURCES.txt
directpy.egg-info/dependency_links.txt
directpy.egg-info/top_level.txt