Metadata-Version: 1.0
Name: directpy
Version: 0.7
Summary: A python library for interacting with DirecTV receivers
Home-page: http://github.com/sentry07/DirectPy
Author: Eric Walters
Author-email: sentry07@gmail.com
License: MIT
Platform: UNKNOWN
